ironmill_oxide/__init__.py
ironmill_oxide/bundler.py
ironmill_oxide/cli/__init__.py
ironmill_oxide/cli/commands/__init__.py
ironmill_oxide/cli/commands/add.py
ironmill_oxide/cli/commands/init.py
ironmill_oxide/cli/commands/install.py
ironmill_oxide/cli/commands/publish.py
ironmill_oxide/cli/commands/rm.py
ironmill_oxide/cli/commands/search.py
ironmill_oxide/cli/get_parser.py
ironmill_oxide/error.py
ironmill_oxide/hash_verifier.py
ironmill_oxide/registry.py
ironmill_oxide/settings.py
ironmill_oxide/util.py
ironmill_oxide-0.1.3.dist-info/METADATA
ironmill_oxide-0.1.3.dist-info/WHEEL
ironmill_oxide-0.1.3.dist-info/entry_points.txt
ironmill_oxide-0.1.3.dist-info/RECORD
