Metadata-Version: 2.1
Name: ironmill-oxide
Version: 0.1.3
Summary: 
Author: IronMill
Requires-Python: >=3.9,<4.0
Classifier: Programming Language :: Python :: 3
Classifier: Programming Language :: Python :: 3.9
Classifier: Programming Language :: Python :: 3.10
Classifier: Programming Language :: Python :: 3.11
Requires-Dist: colorama (>=0.4.6,<0.5.0)
Requires-Dist: prompt-toolkit (>=3.0.39,<4.0.0)
Requires-Dist: requests (>=2.31.0,<3.0.0)
Requires-Dist: semver (>=3.0.1,<4.0.0)
